scrapy_proxycrawl/__init__.py
scrapy_proxycrawl/proxycrawl.py
scrapy_proxycrawl/request.py
scrapy_proxycrawl_middleware-1.1.0.dist-info/LICENSE
scrapy_proxycrawl_middleware-1.1.0.dist-info/METADATA
scrapy_proxycrawl_middleware-1.1.0.dist-info/WHEEL
scrapy_proxycrawl_middleware-1.1.0.dist-info/top_level.txt
scrapy_proxycrawl_middleware-1.1.0.dist-info/RECORD
