Metadata-Version: 2.1
Name: scrapy-proxycrawl-middleware
Version: 1.1.0
Summary: Scrapy ProxyCrawl Proxy Middleware: ProxyCrawl interfacing middleware for Scrapy
Home-page: https://github.com/proxycrawl/scrapy-proxycrawl-middleware
Author: ProxyCrawl
Author-email: info@proxycrawl.com
License: Apache-2.0
Keywords: scrapy middleware scraping scraper crawler crawling proxycrawl api
Platform: UNKNOWN
Classifier: Programming Language :: Python :: 2
Classifier: Programming Language :: Python :: 2.7
Classifier: Programming Language :: Python :: 3
Classifier: Programming Language :: Python :: 3.5
Classifier: Development Status :: 5 - Production/Stable
Classifier: Intended Audience :: Developers
Classifier: License :: OSI Approved :: Apache Software License
Classifier: Operating System :: OS Independent
Classifier: Topic :: Utilities
